torch_io/__init__.py
torch_io/torch_io.py
torch_io/version.py
torch_io-0.1.0a2.dist-info/LICENSE
torch_io-0.1.0a2.dist-info/METADATA
torch_io-0.1.0a2.dist-info/WHEEL
torch_io-0.1.0a2.dist-info/top_level.txt
torch_io-0.1.0a2.dist-info/zip-safe
torch_io-0.1.0a2.dist-info/RECORD
