Metadata-Version: 2.1
Name: torch-io
Version: 0.1.0a2
Summary: TBD
Home-page: https://github.com/prabhuomkar/io
Author: Omkar Prabhu
Author-email: prabhuomkar@pm.me
License: UNKNOWN
Platform: UNKNOWN
Classifier: Development Status :: 1 - Planning
Classifier: Environment :: Plugins
Classifier: Intended Audience :: Developers
Classifier: Intended Audience :: Science/Research
Classifier: License :: OSI Approved :: BSD License
Classifier: Operating System :: MacOS :: MacOS X
Classifier: Operating System :: Microsoft :: Windows
Classifier: Operating System :: POSIX
Classifier: Programming Language :: Python :: 3
Classifier: Topic :: Scientific/Engineering :: Artificial Intelligence
Requires-Dist: torch (>=1.5.1)
